plaquette_unionfind_bindings.cpython-311-x86_64-linux-musl.so
plaquette_unionfind/__init__.py
plaquette_unionfind/unionfind.py
plaquette_unionfind.libs/libgcc_s-a04fdf82.so.1
plaquette_unionfind.libs/libstdc++-a9383cce.so.6.0.28
plaquette_unionfind-0.0.1a2.dist-info/METADATA
plaquette_unionfind-0.0.1a2.dist-info/LICENSE
plaquette_unionfind-0.0.1a2.dist-info/RECORD
plaquette_unionfind-0.0.1a2.dist-info/top_level.txt
plaquette_unionfind-0.0.1a2.dist-info/WHEEL
