Metadata-Version: 2.1
Name: plaquette-unionfind
Version: 0.0.1a2
Project-URL: Homepage, https://docs.plaquette.design/projects/unionfind
Project-URL: Bug Tracker, https://github.com/qc-design/plaquette-unionfind/issues
Keywords: Quantum error correction,qec,quantum computing,fault tolerance,error decoding
Classifier: Development Status :: 3 - Alpha
Classifier: Intended Audience :: Developers
Classifier: Intended Audience :: Science/Research
Classifier: License :: OSI Approved :: Apache Software License
Classifier: Natural Language :: English
Classifier: Programming Language :: Python :: 3
Classifier: Programming Language :: Python :: 3.10
Requires-Python: >=3.10
License-File: LICENSE
Requires-Dist: plaquette
Requires-Dist: plaquette-graph
